.gitignore
README.md
setup.py
wallaby/__init__.py
wallaby/__init__.pyo
wallaby/pf/__init__.py
wallaby/pf/__init__.pyo
wallaby/pf/peer/__init__.py
wallaby/pf/peer/__init__.pyo
wallaby/plugins/__init__.py
wallaby/plugins/__init__.pyo
wallaby/plugins/pdfgenerator/__init__.py
wallaby_plugin_pdfgenerator.egg-info/PKG-INFO
wallaby_plugin_pdfgenerator.egg-info/SOURCES.txt
wallaby_plugin_pdfgenerator.egg-info/dependency_links.txt
wallaby_plugin_pdfgenerator.egg-info/requires.txt
wallaby_plugin_pdfgenerator.egg-info/top_level.txt